{
  "Make": "Canon",
  "Model": "Canon EOS R",
  "Software": "MacroScans v1.0",
  "Orientation": "1",
  "DateTime": "2025:03:13 12:28:59",
  "YCbCrPositioning": "1",
  "XResolution": "72/1",
  "YResolution": "72/1",
  "ResolutionUnit": "2",
  "ExposureTime": "1/100",
  "FNumber": "40/10",
  "ExposureProgram": "1",
  "ExifVersion": "30323331",
  "DateTimeOriginal": "2025:03:13 12:28:59",
  "DateTimeDigitized": "2025:03:13 12:28:59",
  "ComponentsConfiguration": "01020300",
  "CompressedBitsPerPixel": "4/1",
  "ExposureBiasValue": "0/1",
  "MaxApertureValue": "20/10",
  "MeteringMode": "5",
  "Flash": "16",
  "FocalLength": "200/10",
  "MakerNote": "",
  "FlashpixVersion": "30313030",
  "ColorSpace": "1",
  "PixelXDimension": "6720",
  "PixelYDimension": "4480",
  "FileSource": "03",
  "InteroperabilityIndex": "R98",
  "InteroperabilityVersion": "30313030",
  "Copyright": "d",
  "ImageDescription": "Date: 2025:03:13 12:28:59\nSubject: Scan\nArtist: User\nDetail: yaw0_tilt0_forward0\nProject: a\nSubject ID: b\nScale: c\nSoftware: MacroScans v1.0\nCopyright: d\nNotes: e",
  "Artist": "User"
}